LICENSE
README.md
setup.py
deprempy/__init__.py
deprempy.egg-info/PKG-INFO
deprempy.egg-info/SOURCES.txt
deprempy.egg-info/dependency_links.txt
deprempy.egg-info/requires.txt
deprempy.egg-info/top_level.txt