Metadata-Version: 2.1
Name: deprempy
Version: 0.0.9
Summary: Kandilli Rasathanesi aracılığı ile elde edilen deprem sinyallerini kullanarak depremleri gösteren bir Python kütüphanesidir.
Home-page: https://gihtub.com/Meinos10/deprempy
Author: Emre
Author-email: E.tmen2023@gmail.com
License: MIT
Keywords: deprempy,deprempython,deprem,deprem-python,deprem-py
Classifier: Programming Language :: Python :: 3
Classifier: License :: OSI Approved :: MIT License
Classifier: Operating System :: OS Independent
License-File: LICENSE
